Workbook

Sheet Сводка
A1: База позиций США по внешнеполитическим темам
A2: Шкала оценок: от −3 (резко негативно) до +3 (резко позитивно); пустая клетка — тема не затронута. Критерии — над таблицей на листе «Таблица», цитаты — на листе «Цитаты».
A4: Сайт | B4: Документов в таблице
A5: Белый дом | B5: =COUNTIF(Таблица!$A$24:$A$836,"*whitehouse.gov*")
A6: Госдеп | B6: =COUNTIF(Таблица!$A$24:$A$836,"*state.gov*")
A7: Минобороны | B7: =COUNTIF(Таблица!$A$24:$A$836,"*war.gov*")+COUNTIF(Таблица!$A$24:$A$836,"*defense.gov*")
A8: Всего | B8: =SUM(B5:B7)
A10: Тема | B10: Документов с оценкой | C10: Средняя оценка
A11: =Таблица!I23 | B11: =COUNT(Таблица!$I$24:$I$836) | C11: =IF(B11=0,"",AVERAGE(Таблица!$I$24:$I$836))
A12: =Таблица!J23 | B12: =COUNT(Таблица!$J$24:$J$836) | C12: =IF(B12=0,"",AVERAGE(Таблица!$J$24:$J$836))
A13: =Таблица!K23 | B13: =COUNT(Таблица!$K$24:$K$836) | C13: =IF(B13=0,"",AVERAGE(Таблица!$K$24:$K$836))
A14: =Таблица!L23 | B14: =COUNT(Таблица!$L$24:$L$836) | C14: =IF(B14=0,"",AVERAGE(Таблица!$L$24:$L$836))
A15: =Таблица!M23 | B15: =COUNT(Таблица!$M$24:$M$836) | C15: =IF(B15=0,"",AVERAGE(Таблица!$M$24:$M$836))
A16: =Таблица!N23 | B16: =COUNT(Таблица!$N$24:$N$836) | C16: =IF(B16=0,"",AVERAGE(Таблица!$N$24:$N$836))
A17: =Таблица!O23 | B17: =COUNT(Таблица!$O$24:$O$836) | C17: =IF(B17=0,"",AVERAGE(Таблица!$O$24:$O$836))
A18: =Таблица!P23 | B18: =COUNT(Таблица!$P$24:$P$836) | C18: =IF(B18=0,"",AVERAGE(Таблица!$P$24:$P$836))
A19: =Таблица!Q23 | B19: =COUNT(Таблица!$Q$24:$Q$836) | C19: =IF(B19=0,"",AVERAGE(Таблица!$Q$24:$Q$836))
A20: =Таблица!R23 | B20: =COUNT(Таблица!$R$24:$R$836) | C20: =IF(B20=0,"",AVERAGE(Таблица!$R$24:$R$836))
A21: =Таблица!S23 | B21: =COUNT(Таблица!$S$24:$S$836) | C21: =IF(B21=0,"",AVERAGE(Таблица!$S$24:$S$836))
A22: =Таблица!T23 | B22: =COUNT(Таблица!$T$24:$T$836) | C22: =IF(B22=0,"",AVERAGE(Таблица!$T$24:$T$836))
A23: =Таблица!U23 | B23: =COUNT(Таблица!$U$24:$U$836) | C23: =IF(B23=0,"",AVERAGE(Таблица!$U$24:$U$836))
A24: =Таблица!V23 | B24: =COUNT(Таблица!$V$24:$V$836) | C24: =IF(B24=0,"",AVERAGE(Таблица!$V$24:$V$836))
A25: =Таблица!W23 | B25: =COUNT(Таблица!$W$24:$W$836) | C25: =IF(B25=0,"",AVERAGE(Таблица!$W$24:$W$836))

Sheet Таблица
A1: Как читать таблицу
A2: Шкала оценок | B2: от −3 до +3: −3 резко негативно, −2 негативно, −1 скорее негативно, 0 нейтрально/упомянуто без оценки, +1 скорее позитивно, +2 позитивно, +3 резко позитивно. Пустая клетка — тема в документе не затронута.
A3: Основание | B3: к каждой оценке есть дословная цитата из документа — лист «Цитаты» (строки совпадают по ссылке).
A4: Директивность | B4: 1 — указ, прокламация, меморандум, директива, соглашение, стратегия; 0 — заявления, речи, релизы.
A5: Отбор | B5: в таблицу входят только документы, где оценена хотя бы одна тема.
A6: Критерии по темам
A7: Россия | B7: −: Россия как противник, агрессор, санкции против неё; +: переговоры, жесты сближения
A8: Украинский кризис | B8: +: поддержка Украины, помощь, мирное урегулирование; −: давление на Украину
A9: Китай | B9: −2: угроза/противник; −1: конкурент; +1: партнёр по сделке, переговоры
A10: Изменение климата | B10: всегда 0, позиция описывается словами в примечании (напр. «выход из Парижского соглашения»)
A11: Миграция | B11: −3: «вторжение», чрезвычайное положение; −2: нелегальная миграция как угроза; −1: мягкое упоминание; +1: полезная легальная миграция
A12: Глобализация | B12: −: критика «глобализма», международных обязательств; +: поддержка
A13: НАТО | B13: +2: поддержка, похвала; +1: требование делить расходы; −1: «они нам не нужны»
A14: ЕС | B14: +: партнёрство; −: критика
A15: ООН | B15: −2: выход из организаций, резкая критика; −1: критика; +1: работа в органах ООН
A16: Международная торговля | B16: −1: пошлины, «нечестная торговля», дефицит; +1: торговые сделки, открытие рынков
A17: Демократии в мире | B17: +: продвижение демократии и свобод за рубежом; −: отказ от этого
A18: Военные интервенции | B18: +2: одобрение операций и ударов США; −: отказ, сворачивание
... A21: Многополярный мир | B21: +: признание баланса сил/многополярности; −: отрицание
A23: ссылка | B23: страна | C23: дата | D23: кто у власти? | E23: категория документов | F23: язык | G23: институция | H23: директивность | I23: Отношение к России | J23: Отношение к украинскому кризису | K23: Отношение к Китаю | L23: Позиция об изменении климата | M23: Позиция о миграции | N23: Отношение к глобализации | O23: Отношение к НАТО | P23: Отношение к ЕС | Q23: Отношение к ООН и дочерним организациям | R23: Отношение к международной торговле | S23: Позиция о демократиях в мире | T23: Отношение к военным интервенциям | U23: Отношение к продвижению либеральной повестки (аборты, экстремисты-ЛГБТ, легализация наркотиков) | V23: Отношение к Израилю | W23: Отношение к многополярному мировому порядку | X23: примечания (п.13 и прочее)
A24: https://www.war.gov/News/Speeches/Speech/Article/4616486/secretary-of-war-pete-hegseths-state-of-the-force-address-as-delivered | B24: Соединённые Штаты Америки | C24: 1 октября 2026 | D24: Республиканская партия (администрация Д. Трампа) | E24: выступление | F24: английский | G24: Минобороны (П. Хегсет) | H24: 0 | T24: 2 | U24: -2 | X24: либеральная повестка: -2 (отмена DEI, гендерных квот)
A25: https://www.war.gov/News/Releases/Release/Article/4614195/statement-by-chief-pentagon-spokesman-sean-parnell-on-the-conclusion-of-the-us | B25: Соединённые Штаты Америки | C25: 30 сентября 2026 | D25: Республиканская партия (администрация Д. Трампа) | E25: заявление | F25: английский | G25: Минобороны (Ш. Парнелл) | H25: 0 | T25: -1
A26: https://www.war.gov/News/Speeches/Speech/Article/4584638/remarks-by-under-secretary-of-war-for-policy-elbridge-colby-to-natos-north-atla | B26: Соединённые Штаты Америки | C26: 28 августа 2026 | D26: Республиканская партия (администрация Д. Трампа) | E26: выступление | F26: английский | G26: Минобороны (Э. Колби) | H26: 0 | J26: 1 | O26: 1 | P26: 1
A27: https://www.war.gov/News/Releases/Release/Article/4581110/department-of-war-announces-a-750-million-investment-as-part-of-a-155-billion-i | B27: Соединённые Штаты Америки | C27: 24 августа 2026 | D27: Республиканская партия (администрация Д. Трампа) | E27: пресс-релиз | F27: английский | G27: Минобороны | H27: 0 | K27: -2
A28: https://www.war.gov/News/Releases/Release/Article/4575019/department-of-war-orders-research-security-audits-at-30-academic-institutions | B28: Соединённые Штаты Америки | C28: 17 августа 2026 | D28: Республиканская партия (администрация Д. Трампа) | E28: пресс-релиз | F28: английский | G28: Минобороны | H28: 0 | K28: -1
A29: https://www.war.gov/News/Speeches/Speech/Article/4572686/secretary-of-war-pete-hegseth-delivers-remarks-at-the-americas-counter-cartel-c | B29: Соединённые Штаты Америки | C29: 13 августа 2026 | D29: Республиканская партия (администрация Д. Трампа) | E29: выступление | F29: английский | G29: Минобороны (П. Хегсет) | H29: 0 | M29: -3 | N29: -2 | T29: 2 | U29: -2 | X29: либеральная повестка: -2 (критика гендерной повестки)
A30: https://www.war.gov/News/Releases/Release/Article/4553101/the-department-of-war-releases-updated-list-of-foreign-institutions-engaging-in | B30: Соединённые Штаты Америки | C30: 23 июля 2026 | D30: Республиканская партия (администрация Д. Трампа) | E30: пресс-релиз | F30: английский | G30: Минобороны | H30: 0 | I30: -2 | K30: -2
A31: https://www.war.gov/News/Speeches/Speech/Article/4539593/remarks-by-secretary-of-war-pete-hegseth-at-the-2026-nato-defense-ministerial-i | B31: Соединённые Штаты Америки | C31: 14 июля 2026 | D31: Республиканская партия (администрация Д. Трампа) | E31: выступление | F31: английский | G31: Минобороны (П. Хегсет) | H31: 0 | J31: 1 | O31: 1 | P31: -1 | U31: -2 | X31: либеральная повестка: -2 (критика гендерного равенства в НАТО)
A32: https://www.war.gov/News/Speeches/Speech/Article/4522177/remarks-by-under-secretary-of-war-for-policy-elbridge-colby-at-the-ukraine-defe | B32: Соединённые Штаты Америки | C32: 19 июня 2026 | D32: Республиканская партия (администрация Д. Трампа) | E32: выступление | F32: английский | G32: Минобороны (Э. Колби) | H32: 0 | I32: -2 | J32: 2 | O32: 1
A33: https://www.war.gov/News/Releases/Release/Article/4521010/readout-of-secretary-of-war-pete-hegseths-meeting-with-uk-defence-secretary-dan | B33: Соединённые Штаты Америки | C33: 18 июня 2026 | D33: Республиканская партия (администрация Д. Трампа) | E33: пресс-релиз | F33: английский | G33: Минобороны (П. Хегсет) | H33: 0 | J33: 1 | O33: 1
A34: https://www.war.gov/News/Speeches/Speech/Article/4512500/remarks-by-under-secretary-of-war-for-policy-elbridge-colby-at-the-internationa | B34: Соединённые Штаты Америки | C34: 9 июня 2026 | D34: Республиканская партия (администрация Д. Трампа) | E34: выступление | F34: английский | G34: Минобороны (Э. Колби) | H34: 0 | O34: 2
A35: https://www.war.gov/News/Releases/Release/Article/4511232/dow-releases-list-of-chinese-military-companies-in-accordance-with-section-1260 | B35: Соединённые Штаты Америки | C35: 8 июня 2026 | D35: Республиканская партия (администрация Д. Трампа) | E35: пресс-релиз | F35: английский | G35: Минобороны | H35: 0 | K35: -2
A36: https://www.war.gov/News/Releases/Release/Article/4496531/statement-attributable-to-assistant-to-the-secretary-of-war-for-public-affairs | B36: Соединённые Штаты Америки | C36: 19 мая 2026 | D36: Республиканская партия (администрация Д. Трампа) | E36: заявление | F36: английский | G36: Минобороны | H36: 0 | O36: 1
A37: https://www.war.gov/News/Releases/Release/Article/4076184/secretary-of-defense-pete-hegseth-to-travel-to-guantanamo-bay | B37: Соединённые Штаты Америки | C37: 12 мая 2026 | D37: Республиканская партия (администрация Д. Трампа) | E37: пресс-релиз | F37: английский | G37: Минобороны (П. Хегсет) | H37: 0 | M37: -1
A38: https://www.war.gov/News/Speeches/Speech/Article/4442027/remarks-by-under-secretary-of-war-for-policy-elbridge-colby-at-the-ananta-centr | B38: Соединённые Штаты Америки | C38: 24 марта 2026 | D38: Республиканская партия (администрация Д. Трампа) | E38: выступление | F38: английский | G38: Минобороны (Э. Колби) | H38: 0 | R38: 1 | W38: 1
A39: https://www.war.gov/News/Speeches/Speech/Article/4404801/remarks-by-under-secretary-of-war-for-policy-elbridge-colby-at-the-nato-defense | B39: Соединённые Штаты Америки | C39: 12 февраля 2026 | D39: Республиканская партия (администрация Д. Трампа) | E39: выступление | F39: английский | G39: Минобороны (Э. Колби) | H39: 0 | J39: 1 | O39: 1
A40: https://www.war.gov/News/Releases/Release/Article/4333219/joint-media-statement-on-united-states-malaysia-bilateral-meeting | B40: Соединённые Штаты Америки | C40: 26 января 2026 | D40: Республиканская партия (администрация Д. Трампа) | E40: заявление | F40: английский | G40: Минобороны (П. Хегсет) | H40: 0 | K40: -1
A41: https://www.war.gov/News/Releases/Release/Article/4361903/readout-of-december-2025-us-china-defense-policy-coordination-talks | B41: Соединённые Штаты Америки | C41: 17 декабря 2025 | D41: Республиканская партия (администрация Д. Трампа) | E41: пресс-релиз | F41: английский | G41: Минобороны | H41: 0 | K41: 1
A42: https://www.war.gov/News/Speeches/Speech/Article/4354431/remarks-by-secretary-of-war-pete-hegseth-at-the-reagan-national-defense-forum-a | B42: Соединённые Штаты Америки | C42: 9 декабря 2025 | D42: Республиканская партия (администрация Д. Трампа) | E42: выступление | F42: английский | G42: Минобороны (П. Хегсет) | H42: 0 | I42: -1 | J42: 1 | K42: 1 | M42: -2 | O42: 1 | S42: -1 | T42: 2 | U42: -2 | V42: 2 | X42: либеральная повестка: -2 (борьба с «woke»)
A43: https://www.war.gov/News/Releases/Release/Article/4319016/department-of-war-awards-434-million-to-further-on-shore-antimony-trisulfide-pr | B43: Соединённые Штаты Америки | C43: 30 сентября 2025 | D43: Республиканская партия (администрация Д. Трампа) | E43: пресс-релиз | F43: английский | G43: Минобороны | H43: 0 | I43: -1 | K43: -1
A44: https://www.war.gov/News/Releases/Release/Article/4313160/readout-of-secretary-of-war-pete-hegseths-meeting-with-canadian-minister-of-nat | B44: Соединённые Штаты Америки | C44: 24 сентября 2025 | D44: Республиканская партия (администрация Д. Трампа) | E44: пресс-релиз | F44: английский | G44: Минобороны (П. Хегсет) | H44: 0 | O44: 1
A45: https://www.war.gov/News/Releases/Release/Article/4313389/readout-of-secretary-of-war-pete-hegseths-call-with-estonian-minister-of-defenc | B45: Соединённые Штаты Америки | C45: 24 сентября 2025 | D45: Республиканская партия (администрация Д. Трампа) | E45: пресс-релиз | F45: английский | G45: Минобороны (П. Хегсет) | H45: 0 | O45: 2
A46: https://www.war.gov/News/Releases/Release/Article/4299101/readout-of-secretary-of-war-pete-hegseths-call-with-peoples-republic-of-china-m | B46: Соединённые Штаты Америки | C46: 10 сентября 2025 | D46: Республиканская партия (администрация Д. Трампа) | E46: пресс-релиз | F46: английский | G46: Минобороны (П. Хегсет) | H46: 0 | K46: 1
A47: https://www.war.gov/News/Releases/Release/Article/4300023/trump-administration-announces-security-assistance-package-for-lebanon | B47: Соединённые Штаты Америки | C47: 10 сентября 2025 | D47: Республиканская партия (администрация Д. Трампа) | E47: пресс-релиз | F47: английский | G47: Минобороны | H47: 0 | V47: 1
A48: https://www.defense.gov/News/Releases/Release/Article/4270722/office-of-strategic-capital-announces-first-loan-through-dod-agreement-with-mp | B48: Соединённые Штаты Америки | C48: 10 августа 2025 | D48: Республиканская партия (администрация Д. Трампа) | E48: пресс-релиз | F48: английский | G48: Минобороны | H48: 0 | K48: -2
A49: https://www.defense.gov/News/Releases/Release/Article/4244370/readout-of-secretary-of-defense-pete-hegseths-meeting-with-the-federal-minister | B49: Соединённые Штаты Америки | C49: 15 июля 2025 | D49: Республиканская партия (администрация Д. Трампа) | E49: пресс-релиз | F49: английский | G49: Минобороны (П. Хегсет) | H49: 0 | J49: 1 | O49: 1
A50: https://www.defense.gov/News/Releases/Release/Article/4238823/readout-of-secretary-of-defense-pete-hegseths-meeting-with-israel-prime-ministe | B50: Соединённые Штаты Америки | C50: 10 июля 2025 | D50: Республиканская партия (администрация Д. Трампа) | E50: пресс-релиз | F50: английский | G50: Минобороны (П. Хегсет) | H50: 0 | T50: 2 | V50: 2
A51: https://www.defense.gov/News/Releases/Release/Article/4201764/readout-of-secretary-hegseths-meeting-with-southeast-asian-defense-ministers | B51: Соединённые Штаты Америки | C51: 30 мая 2025 | D51: Республиканская партия (администрация Д. Трампа) | E51: пресс-релиз | F51: английский | G51: Минобороны (П. Хегсет) | H51: 0 | K51: -2
A52: https://www.defense.gov/News/Releases/Release/Article/4180537/statement-by-chief-pentagon-spokesman-and-senior-advisor-sean-parnell-on-review | B52: Соединённые Штаты Америки | C52: 10 мая 2025 | D52: Республиканская партия (администрация Д. Трампа) | E52: заявление | F52: английский | G52: Минобороны (Ш. Парнелл) | H52: 1 | U52: -2 | X52: либеральная повестка: -2 (изъятие материалов о гендерной идеологии)
A53: https://www.defense.gov/News/Releases/Release/Article/4151039/statement-by-chief-pentagon-spokesman-sean-parnell | B53: Соединённые Штаты Америки | C53: 10 апреля 2025 | D53: Республиканская партия (администрация Д. Трампа) | E53: заявление | F53: английский | G53: Минобороны (Ш. Парнелл) | H53: 0 | K53: -2
A54: https://www.defense.gov/News/Releases/Release/Article/4149739/joint-statement-between-president-mulino-panama-canal-authority-administrator-a | B54: Соединённые Штаты Америки | C54: 9 апреля 2025 | D54: Республиканская партия (администрация Д. Трампа) | E54: заявление | F54: английский | G54: Минобороны (П. Хегсет) | H54: 0 | K54: -2 | M54: -1
A55: https://www.defense.gov/News/Releases/Release/Article/4148095/readout-of-secretary-of-defense-pete-hegseths-call-with-the-united-kingdoms-sec | B55: Соединённые Штаты Америки | C55: 8 апреля 2025 | D55: Республиканская партия (администрация Д. Трампа) | E55: пресс-релиз | F55: английский | G55: Минобороны (П. Хегсет) | H55: 0 | J55: 1 | T55: 2
A56: https://www.defense.gov/News/Releases/Release/Article/4086539/dod-statement-on-deployment-of-stryker-brigade-combat-team-to-help-secure-our-s | B56: Соединённые Штаты Америки | C56: 1 марта 2025 | D56: Республиканская партия (администрация Д. Трампа) | E56: заявление | F56: английский | G56: Минобороны | H56: 0 | M56: -2
A57: https://www.defense.gov/News/Releases/Release/Article/4079501/pentagon-releases-digital-content-refresh-memorandum | B57: Соединённые Штаты Америки | C57: 27 февраля 2025 | D57: Республиканская партия (администрация Д. Трампа) | E57: пресс-релиз | F57: английский | G57: Минобороны | H57: 1 | U57: -2 | X57: либеральная повестка: -2 (удаление контента о DEI)
A58: https://www.defense.gov/News/Releases/Release/Article/4071336/department-of-defense-chief-of-staff-joseph-kasper-statement-on-us-northcom-com | B58: Соединённые Штаты Америки | C58: 20 февраля 2025 | D58: Республиканская партия (администрация Д. Трампа) | E58: заявление | F58: английский | G58: Минобороны (Д. Каспер) | H58: 0 | M58: -1
A59: https://www.defense.gov/News/Releases/Release/Article/4071371/statement-by-performing-the-duties-of-deputy-secretary-of-defense-robert-g-sale | B59: Соединённые Штаты Америки | C59: 20 февраля 2025 | D59: Республиканская партия (администрация Д. Трампа) | E59: заявление | F59: английский | G59: Минобороны (Р. Салессес) | H59: 0 | L59: 0 | M59: -1 | U59: -2 | X59: либеральная повестка: -2 (отмена DEI); климат: сокращение «климатических» программ
A60: https://www.defense.gov/News/Releases/Release/Article/4068754/readout-of-secretary-of-defense-pete-hegseths-meetings-with-the-president-of-th | B60: Соединённые Штаты Америки | C60: 15 февраля 2025 | D60: Республиканская партия (администрация Д. Трампа) | E60: пресс-релиз | F60: английский | G60: Минобороны (П. Хегсет) | H60: 0 | O60: 1
A61: https://www.defense.gov/News/Releases/Release/Article/4065012/readout-of-secretary-of-defense-pete-hegseths-meeting-with-the-united-kingdoms | B61: Соединённые Штаты Америки | C61: 13 февраля 2025 | D61: Республиканская партия (администрация Д. Трампа) | E61: пресс-релиз | F61: английский | G61: Минобороны (П. Хегсет) | H61: 0 | J61: 1 | O61: 1
A62: https://www.defense.gov/News/Releases/Release/Article/4065017/readout-of-secretary-of-defense-pete-hegseths-meeting-with-german-minister-of-d | B62: Соединённые Штаты Америки | C62: 13 февраля 2025 | D62: Республиканская партия (администрация Д. Трампа) | E62: пресс-релиз | F62: английский | G62: Минобороны (П. Хегсет) | H62: 0 | J62: 1 | O62: 1
A63: https://www.defense.gov/News/Releases/Release/Article/4055479/readout-of-secretary-of-defense-pete-hegseths-meeting-with-israeli-prime-minist | B63: Соединённые Штаты Америки | C63: 6 февраля 2025 | D63: Республиканская партия (администрация Д. Трампа) | E63: пресс-релиз | F63: английский | G63: Минобороны (П. Хегсет) | H63: 0 | V63: 2
A64: https://www.defense.gov/News/Releases/Release/Article/4048247/readout-of-secretary-of-defense-pete-hegseths-call-with-nato-secretary-general | B64: Соединённые Штаты Америки | C64: 30 января 2025 | D64: Республиканская партия (администрация Д. Трампа) | E64: пресс-релиз | F64: английский | G64: Минобороны (П. Хегсет) | H64: 0 | O64: 1
A65: https://www.defense.gov/News/Releases/Release/Article/4047266/readout-of-secretary-of-defense-pete-hegseths-call-with-israel-minister-of-defe | B65: Соединённые Штаты Америки | C65: 29 января 2025 | D65: Республиканская партия (администрация Д. Трампа) | E65: пресс-релиз | F65: английский | G65: Минобороны (П. Хегсет) | H65: 0 | V65: 2
A66: https://www.defense.gov/News/Releases/Release/Article/4041153/readout-of-secretary-of-defense-pete-hegseths-call-with-israeli-prime-minister | B66: Соединённые Штаты Америки | C66: 26 января 2025 | D66: Республиканская партия (администрация Д. Трампа) | E66: пресс-релиз | F66: английский | G66: Минобороны (П. Хегсет) | H66: 0 | V66: 2
A67: https://www.defense.gov/News/Releases/Release/Article/4040940/secretary-hegseths-message-to-the-force | B67: Соединённые Штаты Америки | C67: 25 января 2025 | D67: Республиканская партия (администрация Д. Трампа) | E67: заявление | F67: английский | G67: Минобороны (П. Хегсет) | H67: 0 | K67: -2
A68: https://www.defense.gov/News/Releases/Release/Article/4037500/acting-secretary-of-defense-robert-salesses-statement-on-dod-actions-responding | B68: Соединённые Штаты Америки | C68: 22 января 2025 | D68: Республиканская партия (администрация Д. Трампа) | E68: заявление | F68: английский | G68: Минобороны (Р. Салессес) | H68: 0 | M68: -3
A69: https://www.defense.gov/News/Speeches/Speech/Article/4033764/farewell-remarks-by-secretary-of-defense-lloyd-j-austin-iii-as-delivered | B69: Соединённые Штаты Америки | C69: 18 января 2025 | D69: Демократическая партия (администрация Дж. Байдена) | E69: выступление | F69: английский | G69: Минобороны (Л. Остин) | H69: 0 | I69: -2 | J69: 2 | K69: -2 | O69: 2
A70: https://www.defense.gov/News/Speeches/Speech/Article/4032520/remarks-by-secretary-of-defense-lloyd-j-austin-iii-at-the-armed-forces-farewell | B70: Соединённые Штаты Америки | C70: 16 января 2025 | D70: Демократическая партия (администрация Дж. Байдена) | E70: выступление | F70: английский | G70: Минобороны (Л. Остин) | H70: 0 | I70: -2 | J70: 2 | K70: -1 | O70: 2 | S70: 2 | V70: 2
A71: https://www.defense.gov/News/Releases/Release/Article/4031003/statement-by-secretary-of-defense-lloyd-j-austin-iii-on-the-ceasefire-and-hosta | B71: Соединённые Штаты Америки | C71: 16 января 2025 | D71: Демократическая партия (администрация Дж. Байдена) | E71: заявление | F71: английский | G71: Минобороны (Л. Остин) | H71: 0 | V71: 1
A72: https://www.defense.gov/News/Releases/Release/Article/4010455/assistant-secretary-of-defense-dr-celeste-wallander-chairs-virtual-g7-defense-p | B72: Соединённые Штаты Америки | C72: 21 декабря 2024 | D72: Демократическая партия (администрация Дж. Байдена) | E72: пресс-релиз | F72: английский | G72: Минобороны | H72: 0 | Q72: 1
A73: https://www.defense.gov/News/Releases/Release/Article/4015296/readout-of-secretary-of-defense-lloyd-j-austin-iiis-call-with-german-minister-o | B73: Соединённые Штаты Америки | C73: 21 декабря 2024 | D73: Демократическая партия (администрация Дж. Байдена) | E73: пресс-релиз | F73: английский | G73: Минобороны (Л. Остин) | H73: 0 | J73: 2
A74: https://www.defense.gov/News/Releases/Release/Article/4013717/readout-of-secretary-of-defense-lloyd-j-austin-iiis-call-with-rok-acting-minist | B74: Соединённые Штаты Америки | C74: 20 декабря 2024 | D74: Демократическая партия (администрация Дж. Байдена) | E74: пресс-релиз | F74: английский | G74: Минобороны (Л. Остин) | H74: 0 | S74: 1
A75: https://www.defense.gov/News/Releases/Release/Article/4005820/readout-of-assistant-secretary-of-defense-christopher-p-maiers-meeting-of-the-d | B75: Соединённые Штаты Америки | C75: 18 декабря 2024 | D75: Демократическая партия (администрация Дж. Байдена) | E75: пресс-релиз | F75: английский | G75: Минобороны | H75: 0 | T75: 1
A76: https://www.defense.gov/News/Releases/Release/Article/4010749/dod-releases-chemical-and-biological-defense-program-enterprise-strategy | B76: Соединённые Штаты Америки | C76: 18 декабря 2024 | D76: Демократическая партия (администрация Дж. Байдена) | E76: пресс-релиз | F76: английский | G76: Минобороны | H76: 1 | I76: -2 | K76: -2
A77: https://www.defense.gov/News/Releases/Release/Article/4006952/readout-of-secretary-of-defense-lloyd-j-austin-iiis-call-with-qatari-deputy-pri | B77: Соединённые Штаты Америки | C77: 17 декабря 2024 | D77: Демократическая партия (администрация Дж. Байдена) | E77: пресс-релиз | F77: английский | G77: Минобороны (Л. Остин) | H77: 0 | T77: 1 | V77: 1
A78: https://www.state.gov/releases/office-of-the-spokesman/2026/07/sanctioning-over-50-targets-linked-to-cartel-de-jalisco-nueva-generacion | B78: Соединённые Штаты Америки | C78: 4 октября 2026 | D78: Республиканская партия (администрация Д. Трампа) | E78: заявление | F78: английский | G78: Госдеп (Т. Пиготт) | H78: 0 | M78: -1
A79: https://www.state.gov/releases/office-of-the-spokesman/2026/07/u-s-department-of-state-and-u-s-department-of-health-and-human-services-on-strengthening-vaccine-safety-accountability-and-american-leadership-in-global-health | B79: Соединённые Штаты Америки | C79: 4 октября 2026 | D79: Республиканская партия (администрация Д. Трампа) | E79: пресс-релиз | F79: английский | G79: Госдеп | H79: 0 | Q79: -2
A80: https://www.state.gov/releases/office-of-the-spokesman/2026/10/joint-statement-on-the-anniversary-of-the-snapback-of-un-restrictions-on-and-related-to-iran | B80: Соединённые Штаты Америки | C80: 4 октября 2026 | D80: Республиканская партия (администрация Д. Трампа) | E80: заявление | F80: английский | G80: Госдеп | H80: 0 | Q80: 1
A81: https://www.state.gov/releases/office-of-the-spokesman/2026/02/secretary-rubios-meeting-with-director-of-the-office-of-the-ccp-central-foreign-affairs-commission-and-chinas-foreign-minister-wang-yi | B81: Соединённые Штаты Америки | C81: 3 октября 2026 | D81: Республиканская партия (администрация Д. Трампа) | E81: пресс-релиз | F81: английский | G81: Госдеп (Т. Пиготт) | H81: 0 | K81: 1
A82: https://www.state.gov/releases/office-of-the-spokesman/2026/03/secretary-of-state-marco-rubio-remarks-to-press-8 | B82: Соединённые Штаты Америки | C82: 3 октября 2026 | D82: Республиканская партия (администрация Д. Трампа) | E82: интервью | F82: английский | G82: Госдеп (М. Рубио) | H82: 0 | I82: 1 | J82: 1 | T82: 2
A83: https://www.state.gov/releases/office-of-the-spokesman/2026/05/disrupting-irans-overseas-military-procurement-networks | B83: Соединённые Штаты Америки | C83: 30 сентября 2026 | D83: Республиканская партия (администрация Д. Трампа) | E83: пресс-релиз | F83: английский | G83: Госдеп | H83: 0 | K83: -2
A84: https://www.state.gov/releases/office-of-the-spokesman/2026/06/secretary-of-state-marco-rubio-remarks-to-press-12 | B84: Соединённые Штаты Америки | C84: 30 сентября 2026 | D84: Республиканская партия (администрация Д. Трампа) | E84: интервью | F84: английский | G84: Госдеп (М. Рубио) | H84: 0 | J84: 1 | O84: 1 | P84: -1 | V84: 1
A85: https://www.state.gov/releases/office-of-the-spokesman/2026/07/secretary-of-state-marco-rubio-remarks-to-the-press-15 | B85: Соединённые Штаты Америки | C85: 30 сентября 2026 | D85: Республиканская партия (администрация Д. Трампа) | E85: интервью | F85: английский | G85: Госдеп (М. Рубио) | H85: 0 | J85: 1 | K85: 1 | O85: 1
A86: https://www.state.gov/releases/office-of-the-spokesman/2026/08/u-s-participation-in-special-meeting-at-the-oas-permanent-council-on-nicaragua | B86: Соединённые Штаты Америки | C86: 30 сентября 2026 | D86: Республиканская партия (администрация Д. Трампа) | E86: пресс-релиз | F86: английский | G86: Госдеп | H86: 0 | S86: 2
A87: https://www.state.gov/releases/office-of-the-spokesman/2026/09/united-states-disrupts-irans-proliferation-sensitive-efforts-in-support-of-un-restrictions | B87: Соединённые Штаты Америки | C87: 30 сентября 2026 | D87: Республиканская партия (администрация Д. Трампа) | E87: заявление | F87: английский | G87: Госдеп (Т. Пиготт) | H87: 0 | I87: -1 | K87: -1 | Q87: 1
A88: https://www.state.gov/releases/office-of-the-spokesman/2026/09/united-states-disrupts-irans-proliferation-sensitive-efforts-in-support-of-un-restrictions-fact-sheet | B88: Соединённые Штаты Америки | C88: 30 сентября 2026 | D88: Республиканская партия (администрация Д. Трампа) | E88: пресс-релиз | F88: английский | G88: Госдеп | H88: 0 | I88: -2
A89: https://www.state.gov/releases/office-of-the-spokesman/2026/09/secretary-of-state-marco-rubio-at-the-trump-administrations-foundry-school-launch | B89: Соединённые Штаты Америки | C89: 29 сентября 2026 | D89: Республиканская партия (администрация Д. Трампа) | E89: выступление | F89: английский | G89: Госдеп (М. Рубио) | H89: 0 | N89: -2 | R89: -1
A90: https://www.state.gov/releases/office-of-the-spokesman/2026/06/joint-statement-on-sudan-political-track | B90: Соединённые Штаты Америки | C90: 26 сентября 2026 | D90: Республиканская партия (администрация Д. Трампа) | E90: заявление | F90: английский | G90: Госдеп | H90: 0 | S90: 1
A91: https://www.state.gov/releases/office-of-the-spokesman/2026/07/secretary-of-state-marco-rubio-remarks-to-the-press-14 | B91: Соединённые Штаты Америки | C91: 26 сентября 2026 | D91: Республиканская партия (администрация Д. Трампа) | E91: интервью | F91: английский | G91: Госдеп (М. Рубио) | H91: 0 | I91: 1 | J91: 1 | K91: 1 | M91: -1 | T91: 2
A92: https://www.state.gov/releases/office-of-the-spokesman/2026/08/state-department-establishes-task-force-to-end-birth-tourism | B92: Соединённые Штаты Америки | C92: 26 сентября 2026 | D92: Республиканская партия (администрация Д. Трампа) | E92: пресс-релиз | F92: английский | G92: Госдеп | H92: 0 | M92: -2
A93: https://www.state.gov/releases/office-of-the-spokesman/2025/05/imposing-sanctions-on-china-and-iran-based-entities-and-individuals-that-support-irans-ballistic-missile-program | B93: Соединённые Штаты Америки | C93: 26 сентября 2026 | D93: Республиканская партия (администрация Д. Трампа) | E93: заявление | F93: английский | G93: Госдеп (Т. Брюс) | H93: 0 | K93: -2
A94: https://www.state.gov/releases/office-of-the-spokesman/2025/06/luxembourg-national-day | B94: Соединённые Штаты Америки | C94: 26 сентября 2026 | D94: Республиканская партия (администрация Д. Трампа) | E94: заявление | F94: английский | G94: Госдеп (М. Рубио) | H94: 0 | O94: 2
A95: https://www.state.gov/releases/office-of-the-spokesman/2026/03/the-united-states-to-host-the-shield-of-the-americas-summit | B95: Соединённые Штаты Америки | C95: 25 сентября 2026 | D95: Республиканская партия (администрация Д. Трампа) | E95: пресс-релиз | F95: английский | G95: Госдеп | H95: 0 | M95: -2
A96: https://www.state.gov/releases/office-of-the-spokesman/2026/06/joint-statement-by-members-of-the-shield-of-the-americas-2 | B96: Соединённые Штаты Америки | C96: 25 сентября 2026 | D96: Республиканская партия (администрация Д. Трампа) | E96: заявление | F96: английский | G96: Госдеп | H96: 0 | S96: 2
A97: https://www.state.gov/releases/office-of-the-spokesman/2026/07/united-states-sanctioning-irans-mahan-air-network-and-irgc-linked-front-company | B97: Соединённые Штаты Америки | C97: 24 сентября 2026 | D97: Республиканская партия (администрация Д. Трампа) | E97: заявление | F97: английский | G97: Госдеп (Т. Пиготт) | H97: 0 | I97: -1 | K97: -1
A98: https://www.state.gov/releases/office-of-the-spokesman/2026/09/joint-statement-on-the-launch-of-the-andes-atlantic-corridor | B98: Соединённые Штаты Америки | C98: 24 сентября 2026 | D98: Республиканская партия (администрация Д. Трампа) | E98: соглашение | F98: английский | G98: Госдеп | H98: 0 | R98: 1
A99: https://www.state.gov/releases/office-of-the-spokesman/2026/09/secretary-of-state-marco-rubio-remarks-to-press-13 | B99: Соединённые Штаты Америки | C99: 24 сентября 2026 | D99: Республиканская партия (администрация Д. Трампа) | E99: интервью | F99: английский | G99: Госдеп (М. Рубио) | H99: 0 | I99: -1 | K99: -1 | R99: 1 | V99: 1
A100: https://www.state.gov/releases/office-of-the-spokesman/2026/09/secretary-of-state-marco-rubio-remarks-to-press-16 | B100: Соединённые Штаты Америки | C100: 24 сентября 2026 | D100: Республиканская партия (администрация Д. Трампа) | E100: интервью | F100: английский | G100: Госдеп (М. Рубио) | H100: 0 | J100: 1 | K100: 1 | Q100: -1 | R100: -1 | V100: 1
A101: https://www.state.gov/releases/office-of-the-spokesman/2026/09/united-states-and-argentina-launch-andes-atlantic-corridor-fact-sheet | B101: Соединённые Штаты Америки | C101: 24 сентября 2026 | D101: Республиканская партия (администрация Д. Трампа) | E101: пресс-релиз | F101: английский | G101: Госдеп | H101: 0 | R101: 1
A102: https://www.state.gov/releases/office-of-the-spokesman/2026/09/united-states-pledges-additional-life-saving-health-assistance-in-response-to-ebola-outbreak | B102: Соединённые Штаты Америки | C102: 24 сентября 2026 | D102: Республиканская партия (администрация Д. Трампа) | E102: пресс-релиз | F102: английский | G102: Госдеп | H102: 0 | Q102: 1
A103: https://www.state.gov/releases/office-of-the-spokesman/2025/06/sweden-national-day | B103: Соединённые Штаты Америки | C103: 24 сентября 2026 | D103: Республиканская партия (администрация Д. Трампа) | E103: заявление | F103: английский | G103: Госдеп (М. Рубио) | H103: 0 | O103: 2
...

Sheet Цитаты
A1: ссылка | B1: Отношение к России | C1: Отношение к украинскому кризису | D1: Отношение к Китаю | E1: Позиция об изменении климата | F1: Позиция о миграции | G1: Отношение к глобализации | H1: Отношение к НАТО | I1: Отношение к ЕС | J1: Отношение к ООН и дочерним организациям | K1: Отношение к международной торговле | L1: Позиция о демократиях в мире | M1: Отношение к военным интервенциям | N1: Отношение к продвижению либеральной повестки (аборты, экстремисты-ЛГБТ, легализация наркотиков) | O1: Отношение к Израилю | P1: Отношение к многополярному мировому порядку
A2: https://www.war.gov/News/Speeches/Speech/Article/4616486/secretary-of-war-pete-hegseths-state-of-the-force-address-as-delivered | M2: these Americans, right here, and their peers, these — have destroyed Iran's Navy | N2: No more diversity quotas, no more gender pronouns, no more identity months.
A3: https://www.war.gov/News/Releases/Release/Article/4614195/statement-by-chief-pentagon-spokesman-sean-parnell-on-the-conclusion-of-the-us | M3: The primary responsibility for addressing Iraq's remaining security challenges…now rests with the Government of Iraq
A4: https://www.war.gov/News/Speeches/Speech/Article/4584638/remarks-by-under-secretary-of-war-for-policy-elbridge-colby-to-natos-north-atla | C4: our allies can and will lead in supporting Ukraine's self-defense | H4: with our allies taking primary responsibility for Europe's conventional defense | I4: the goal is for Europeans to be partners, not dependencies
A5: https://www.war.gov/News/Releases/Release/Article/4581110/department-of-war-announces-a-750-million-investment-as-part-of-a-155-billion-i | D5: This initiative aggressively addresses an over-dependence on China for rare-earth elements.
A6: https://www.war.gov/News/Releases/Release/Article/4575019/department-of-war-orders-research-security-audits-at-30-academic-institutions | D6: organizations associated with rebranded Confucius Institutes
A7: https://www.war.gov/News/Speeches/Speech/Article/4572686/secretary-of-war-pete-hegseth-delivers-remarks-at-the-americas-counter-cartel-c | F7: openly accepting mass illegal immigration and destroying many of our great American cities — an invasion, no doubt. | G7: Under decades of globalist neglect more than 1 million Americans died from fentanyl | M7: It's now nearly one year since the launch of Operation Southern Spear…And it has been a resounding success thus far. | N7: promoting priorities like gender issues, women, peace and security, or climate change or diversity — dudes in dresses.
A8: https://www.war.gov/News/Releases/Release/Article/4553101/the-department-of-war-releases-updated-list-of-foreign-institutions-engaging-in | B8: The FY25 list formally identifies 130 academic and research institutions located in China, Russia and Iran. | D8: The FY25 list formally identifies 130 academic and research institutions located in China, Russia and Iran.
A9: https://www.war.gov/News/Speeches/Speech/Article/4539593/remarks-by-secretary-of-war-pete-hegseth-at-the-2026-nato-defense-ministerial-i | C9: allies have taken the lead in funding support for Ukraine's defense | H9: for too long, NATO has been a paper tiger and a one-way street | I9: Europe's borders flew wide open, welfare states expanded, defense budgets cratered | N9: the focus had been on gender equity and climate change and defense austerity
A10: https://www.war.gov/News/Speeches/Speech/Article/4522177/remarks-by-under-secretary-of-war-for-policy-elbridge-colby-at-the-ukraine-defe | B10: Russia's understanding that perpetuating this war is not only condemnable but also will not pay off for Moscow | C10: Ukraine's defense does hold but continued and sustained support from allies is essential to maintain it. | H10: It is important that NATO allies continue — and indeed, increase — their support for Ukraine's defense
A11: https://www.war.gov/News/Releases/Release/Article/4521010/readout-of-secretary-of-war-pete-hegseths-meeting-with-uk-defence-secretary-dan | C11: including support for Ukraine's defense | H11: the critical need for all allies…to show rapid progress toward their Hague Summit pledge of 5% of GDP on defense spending
A12: https://www.war.gov/News/Speeches/Speech/Article/4512500/remarks-by-under-secretary-of-war-for-policy-elbridge-colby-at-the-internationa | H12: are striving together to build a renewed NATO
A13: https://www.war.gov/News/Releases/Release/Article/4511232/dow-releases-list-of-chinese-military-companies-in-accordance-with-section-1260 | D13: names of "Chinese military companies" operating directly or indirectly in the United States
A14: https://www.war.gov/News/Releases/Release/Article/4496531/statement-attributable-to-assistant-to-the-secretary-of-war-for-public-affairs | H14: incentivizing and enabling our NATO allies to take primary responsibility for Europe's conventional defense
A15: https://www.war.gov/News/Releases/Release/Article/4076184/secretary-of-defense-pete-hegseth-to-travel-to-guantanamo-bay | F15: It also facilitates temporary detention of illegal aliens who are pending return to their country of origin
A16: https://www.war.gov/News/Speeches/Speech/Article/4442027/remarks-by-under-secretary-of-war-for-policy-elbridge-colby-at-the-ananta-centr | K16: Both benefit from open trade and national autonomy. | P16: Both of our countries benefit from an Indo-Pacific in which no power can dominate the region.
A17: https://www.war.gov/News/Speeches/Speech/Article/4404801/remarks-by-under-secretary-of-war-for-policy-elbridge-colby-at-the-nato-defense | C17: negotiate an end to the tragic war in Ukraine | H17: This "NATO 3.0" requires much greater efforts by our allies to step up and assume primary responsibility for the conventional defense of Europe.
A18: https://www.war.gov/News/Releases/Release/Article/4333219/joint-media-statement-on-united-states-malaysia-bilateral-meeting | D18: grey-zone tactics, such as hydrographic research conducted under the protection of foreign coast guard vessels, threaten sovereignty
A19: https://www.war.gov/News/Releases/Release/Article/4361903/readout-of-december-2025-us-china-defense-policy-coordination-talks | D19: achieve a stable peace and respectful relations between the United States and China
A20: https://www.war.gov/News/Speeches/Speech/Article/4354431/remarks-by-secretary-of-war-pete-hegseth-at-the-reagan-national-defense-forum-a | B20: Vladimir Putin saw the open door and he took it | C20: we are working tirelessly to end the tragic war in Ukraine | D20: relations between the United States and China are better and stronger than they've been in many years | F20: tens of millions of illegals | H20: NATO committed to spend 5% of GDP | L20: the War Department will not be distracted by democracy building interventionism | M20: With Operation Midnight Hammer, the world saw, after decades of hemming and hawing, the decisive effect of American military strength | N20: Wokeness, weakness, war. | O20: Model allies that step up like Israel
A21: https://www.war.gov/News/Releases/Release/Article/4319016/department-of-war-awards-434-million-to-further-on-shore-antimony-trisulfide-pr | B21: China and Russia control the market for antimony and all its derivatives, putting the United States at risk | D21: China and Russia control the market for antimony and all its derivatives, putting the United States at risk
A22: https://www.war.gov/News/Releases/Release/Article/4313160/readout-of-secretary-of-war-pete-hegseths-meeting-with-canadian-minister-of-nat | H22: vital importance of Canada stepping up to meet its historic Hague Summit commitment
A23: https://www.war.gov/News/Releases/Release/Article/4313389/readout-of-secretary-of-war-pete-hegseths-call-with-estonian-minister-of-defenc | H23: the Department of War stands with all NATO allies and that any incursion into NATO airspace is unacceptable
A24: https://www.war.gov/News/Releases/Release/Article/4299101/readout-of-secretary-of-war-pete-hegseths-call-with-peoples-republic-of-china-m | D24: the United States does not seek conflict with China nor is it pursuing regime change or strangulation of the PRC
A25: https://www.war.gov/News/Releases/Release/Article/4300023/trump-administration-announces-security-assistance-package-for-lebanon | O25: in support of the November 2024 Cessation of Hostilities between Lebanon and Israel
A26: https://www.defense.gov/News/Releases/Release/Article/4270722/office-of-strategic-capital-announces-first-loan-through-dod-agreement-with-mp | D26: The Chinese Communist Party has implemented aggressive actions to endanger the global critical minerals supply chain
A27: https://www.defense.gov/News/Releases/Release/Article/4244370/readout-of-secretary-of-defense-pete-hegseths-meeting-with-the-federal-minister | C27: set conditions for an end to the war in Ukraine on terms that support an enduring peace | H27: securing historic commitments by NATO allies at last month's NATO Summit at The Hague to meet President Trump's call to spend 5% of GDP on defense
A28: https://www.defense.gov/News/Releases/Release/Article/4238823/readout-of-secretary-of-defense-pete-hegseths-meeting-with-israel-prime-ministe | M28: brave U.S. servicemembers who executed this perfect operation | O28: the United States remains committed to supporting Israel
A29: https://www.defense.gov/News/Releases/Release/Article/4201764/readout-of-secretary-hegseths-meeting-with-southeast-asian-defense-ministers | D29: Secretary Hegseth reiterated concerns about coercive activity by China against South China Sea claimant countries
A30: https://www.defense.gov/News/Releases/Release/Article/4180537/statement-by-chief-pentagon-spokesman-and-senior-advisor-sean-parnell-on-review | N30: should be mission-focused and not promote divisive concepts and gender ideology
A31: https://www.defense.gov/News/Releases/Release/Article/4151039/statement-by-chief-pentagon-spokesman-sean-parnell | D31: We are taking back the Panama Canal from malign Chinese influence
A32: https://www.defense.gov/News/Releases/Release/Article/4149739/joint-statement-between-president-mulino-panama-canal-authority-administrator-a | D32: exit the Belt and Road Initiative, and to reduce China's problematic presence | F32: Panama's efforts to reduce illegal immigration and for closing the border in the Darién
A33: https://www.defense.gov/News/Releases/Release/Article/4148095/readout-of-secretary-of-defense-pete-hegseths-call-with-the-united-kingdoms-sec | C33: thanked the UK for its leadership in chairing the Ukraine Defense Contact Group | M33: the recent strikes against the Houthi terrorists in Yemen
A34: https://www.defense.gov/News/Releases/Release/Article/4086539/dod-statement-on-deployment-of-stryker-brigade-combat-team-to-help-secure-our-s | F34: to seal the border and protect the territorial integrity of the United States
A35: https://www.defense.gov/News/Releases/Release/Article/4079501/pentagon-releases-digital-content-refresh-memorandum | N35: remove and archive DoD news articles, photos, and videos promoting Diversity, Equity, and Inclusion (DEI)
A36: https://www.defense.gov/News/Releases/Release/Article/4071336/department-of-defense-chief-of-staff-joseph-kasper-statement-on-us-northcom-com | F36: cooperation on security along the Mexico and U.S. border
A37: https://www.defense.gov/News/Releases/Release/Article/4071371/statement-by-performing-the-duties-of-deputy-secretary-of-defense-robert-g-sale | E37: so-called "climate change" and other woke programs | F37: Securing our borders | N37: ending radical and wasteful government DEI programs and preferencing
A38: https://www.defense.gov/News/Releases/Release/Article/4068754/readout-of-secretary-of-defense-pete-hegseths-meetings-with-the-president-of-th | H38: Poland is a model ally on defense spending and modernization efforts — setting the example for NATO burden-sharing commitments
A39: https://www.defense.gov/News/Releases/Release/Article/4065012/readout-of-secretary-of-defense-pete-hegseths-meeting-with-the-united-kingdoms | C39: the need to set the stage for negotiations to stop the fighting and reach an enduring peace | H39: greater burden-sharing by European Allies
A40: https://www.defense.gov/News/Releases/Release/Article/4065017/readout-of-secretary-of-defense-pete-hegseths-meeting-with-german-minister-of-d | C40: supporting diplomatic efforts to achieve a durable peace in Ukraine | H40: a strong focus on Allied defense spending
A41: https://www.defense.gov/News/Releases/Release/Article/4055479/readout-of-secretary-of-defense-pete-hegseths-meeting-with-israeli-prime-minist | O41: the United States remains 100 percent committed to Israel's security
A42: https://www.defense.gov/News/Releases/Release/Article/4048247/readout-of-secretary-of-defense-pete-hegseths-call-with-nato-secretary-general | H42: building a stronger, more lethal NATO Alliance. Both leaders stressed the importance of raising Allied defense spending
A43: https://www.defense.gov/News/Releases/Release/Article/4047266/readout-of-secretary-of-defense-pete-hegseths-call-with-israel-minister-of-defe | O43: the United States fully supports Israel's right to defend itself, and that Israel is a model ally for the region
A44: https://www.defense.gov/News/Releases/Release/Article/4041153/readout-of-secretary-of-defense-pete-hegseths-call-with-israeli-prime-minister | O44: to ensure that Israel has the capabilities it needs to defend itself
A45: https://www.defense.gov/News/Releases/Release/Article/4040940/secretary-hegseths-message-to-the-force | D45: deter aggression in the Indo-Pacific by Communist China
A46: https://www.defense.gov/News/Releases/Release/Article/4037500/acting-secretary-of-defense-robert-salesses-statement-on-dod-actions-responding | F46: President Trump declared that a national emergency exists at the southern border of the United States
A47: https://www.defense.gov/News/Speeches/Speech/Article/4033764/farewell-remarks-by-secretary-of-defense-lloyd-j-austin-iii-as-delivered | B47: Putin's imperial aggression | C47: We've rallied the free world to help Ukraine fight for its freedom | D47: the "pacing challenge" from the People's Republic of China | H47: We've led a NATO alliance that is stronger, larger, and more united than ever.
A48: https://www.defense.gov/News/Speeches/Speech/Article/4032520/remarks-by-secretary-of-defense-lloyd-j-austin-iii-at-the-armed-forces-farewell | B48: Putin's indefensible invasion | C48: He rallied the free world to help Ukraine fight for its freedom | D48: strategic competition with the People's Republic of China | H48: He reinforced NATO—which is now larger, stronger, and more united than ever. | L48: President Biden showed the world the strength and the resolve that only a democracy can muster. | O48: He shored up Israel's security after the vile October 7th terrorist assault by Hamas.
A49: https://www.defense.gov/News/Releases/Release/Article/4031003/statement-by-secretary-of-defense-lloyd-j-austin-iii-on-the-ceasefire-and-hosta | O49: I am pleased that Israel and Hamas have today secured a ceasefire and hostage-release deal
A50: https://www.defense.gov/News/Releases/Release/Article/4010455/assistant-secretary-of-defense-dr-celeste-wallander-chairs-virtual-g7-defense-p | J50: the important role of the UN Interim Force in Lebanon (UNIFIL)
A51: https://www.defense.gov/News/Releases/Release/Article/4015296/readout-of-secretary-of-defense-lloyd-j-austin-iiis-call-with-german-minister-o | C51: Germany's continued substantial security assistance to Ukraine
A52: https://www.defense.gov/News/Releases/Release/Article/4013717/readout-of-secretary-of-defense-lloyd-j-austin-iiis-call-with-rok-acting-minist | L52: shared commitment to the democratic institutions and processes of the ROK
A53: https://www.defense.gov/News/Releases/Release/Article/4005820/readout-of-assistant-secretary-of-defense-christopher-p-maiers-meeting-of-the-d | M53: ensure the enduring defeat of ISIS
A54: https://www.defense.gov/News/Releases/Release/Article/4010749/dod-releases-chemical-and-biological-defense-program-enterprise-strategy | B54: Russia as the acute threat | D54: the People's Republic of China as the pacing challenge
A55: https://www.defense.gov/News/Releases/Release/Article/4006952/readout-of-secretary-of-defense-lloyd-j-austin-iiis-call-with-qatari-deputy-pri | M55: degrade Houthi military capabilities | O55: support implementation of the ceasefire between Israel and Lebanon
A56: https://www.state.gov/releases/office-of-the-spokesman/2026/07/sanctioning-over-50-targets-linked-to-cartel-de-jalisco-nueva-generacion | F56: traffics illegal immigrants
A57: https://www.state.gov/releases/office-of-the-spokesman/2026/07/u-s-department-of-state-and-u-s-department-of-health-and-human-services-on-strengthening-vaccine-safety-accountability-and-american-leadership-in-global-health | J57: it will not provide U.S. Government funding to the World Health Organization through Gavi
A58: https://www.state.gov/releases/office-of-the-spokesman/2026/10/joint-statement-on-the-anniversary-of-the-snapback-of-un-restrictions-on-and-related-to-iran | J58: We urge all UN Member States to implement these resolutions
A59: https://www.state.gov/releases/office-of-the-spokesman/2026/02/secretary-rubios-meeting-with-director-of-the-office-of-the-ccp-central-foreign-affairs-commission-and-chinas-foreign-minister-wang-yi | D59: The meeting was positive and constructive.
A60: https://www.state.gov/releases/office-of-the-spokesman/2026/03/secretary-of-state-marco-rubio-remarks-to-press-8 | B60: it is important for nuclear powers to have some engagement at the governmental level | C60: we want to see the end of that war | M60: We’re going to destroy Iran’s navy, destroy their air force.
A61: https://www.state.gov/releases/office-of-the-spokesman/2026/05/disrupting-irans-overseas-military-procurement-networks | D61: hold China-based entities accountable for their support to Iran
A62: https://www.state.gov/releases/office-of-the-spokesman/2026/06/secretary-of-state-marco-rubio-remarks-to-press-12 | C62: to play whatever constructive role we can to bring about an enduring end to this war in Ukraine | H62: one of the reasons why I’ve been a strong supporter of our presence in NATO is because it allows us these basing rights | I62: many European countries did not step up and do enough | O62: for the first time in 30 years, the sovereign Government of Lebanon is speaking to the Government of Israel directly
A63: https://www.state.gov/releases/office-of-the-spokesman/2026/07/secretary-of-state-marco-rubio-remarks-to-the-press-15 | C63: in order to end this war will require something that both Russia and Ukraine can agree to | D63: We have to have a relationship with China and we want it to be as positive as it possibly can be. | H63: We sell arms via PURL, which is an initiative we have through NATO.
A64: https://www.state.gov/releases/office-of-the-spokesman/2026/08/u-s-participation-in-special-meeting-at-the-oas-permanent-council-on-nicaragua | L64: support the Nicaraguan people’s right to a future free from tyranny
A65: https://www.state.gov/releases/office-of-the-spokesman/2026/09/united-states-disrupts-irans-proliferation-sensitive-efforts-in-support-of-un-restrictions | B65: due to the obstruction of Russia and China | D65: due to the obstruction of Russia and China | J65: The United States calls on all UN Member States to fully implement their binding obligations.
A66: https://www.state.gov/releases/office-of-the-spokesman/2026/09/united-states-disrupts-irans-proliferation-sensitive-efforts-in-support-of-un-restrictions-fact-sheet | B66: Russia has now delivered to Iran nearly all of its reportedly 24 contracted Yak-130 aircraft.
A67: https://www.state.gov/releases/office-of-the-spokesman/2026/09/secretary-of-state-marco-rubio-at-the-trump-administrations-foundry-school-launch | G67: There was this fantasy, really, that the whole world would become a free enterprise, democracies, and that everyone would look us. | K67: we traded our industrial base for the illusion of cheap abundance
A68: https://www.state.gov/releases/office-of-the-spokesman/2026/06/joint-statement-on-sudan-political-track | L68: a peaceful, democratic, and stable future for the country
A69: https://www.state.gov/releases/office-of-the-spokesman/2026/07/secretary-of-state-marco-rubio-remarks-to-the-press-14 | B69: We have to have a relationship with the Russian Government, even though we have areas of disagreement | C69: We think it would be good for Russia if that war came to an end. | D69: it’s important for us to continue to talk to China, irrespective of our differences | F69: the threat of mass migration | M69: The United States is defending that shipping and, in addition, is targeting the places that are launching against those ships
A70: https://www.state.gov/releases/office-of-the-spokesman/2026/08/state-department-establishes-task-force-to-end-birth-tourism | F70: citizenship is not a commodity to be acquired through the calculated exploitation of U.S. immigration laws
A71: https://www.state.gov/releases/office-of-the-spokesman/2025/05/imposing-sanctions-on-china-and-iran-based-entities-and-individuals-that-support-irans-ballistic-missile-program | D71: This is another example of how the CCP and China-based companies provide key economic and technical support to Iran and its proxies
A72: https://www.state.gov/releases/office-of-the-spokesman/2025/06/luxembourg-national-day | H72: Luxembourg’s decision to spend more on national defense strengthens our NATO Alliance for future generations.
A73: https://www.state.gov/releases/office-of-the-spokesman/2026/03/the-united-states-to-host-the-shield-of-the-americas-summit | F73: illegal and mass immigration
A74: https://www.state.gov/releases/office-of-the-spokesman/2026/06/joint-statement-by-members-of-the-shield-of-the-americas-2 | L74: We stand with Paz’s democratic government
A75: https://www.state.gov/releases/office-of-the-spokesman/2026/07/united-states-sanctioning-irans-mahan-air-network-and-irgc-linked-front-company | B75: six entities and individuals in China, India, Russia, and Iran | D75: six entities and individuals in China, India, Russia, and Iran
A76: https://www.state.gov/releases/office-of-the-spokesman/2026/09/joint-statement-on-the-launch-of-the-andes-atlantic-corridor | K76: Agreement on Reciprocal Trade and Investment
A77: https://www.state.gov/releases/office-of-the-spokesman/2026/09/secretary-of-state-marco-rubio-remarks-to-press-13 | B77: the Chinese and Russian companies held these fields but never turned them into anything | D77: the Chinese and Russian companies held these fields but never turned them into anything | K77: We’re hoping to wrap up good, solid trade deals with all three of these countries | O77: Obviously, we’re not going to do what the UK did.
A78: https://www.state.gov/releases/office-of-the-spokesman/2026/09/secretary-of-state-marco-rubio-remarks-to-press-16 | C78: Ultimately, we all want this war to end | D78: The relationship between the United States and China will define the 21st century | J78: the United Nations, for example, has tremendous potential, but it’s not living up to it | K78: the President is a very strong believer in tariffs as a tool of national policy | O78: the last thing that Israel needs or the region needs is an additional crisis
A79: https://www.state.gov/releases/office-of-the-spokesman/2026/09/united-states-and-argentina-launch-andes-atlantic-corridor-fact-sheet | K79: increase trade flows
A80: https://www.state.gov/releases/office-of-the-spokesman/2026/09/united-states-pledges-additional-life-saving-health-assistance-in-response-to-ebola-outbreak | J80: our $1.8 billion in assistance to the UN Office for the Coordination of Humanitarian Affairs
A81: https://www.state.gov/releases/office-of-the-spokesman/2025/06/sweden-national-day | H81: As NATO Allies, we stand together to ensure a safer, more secure world.
A82: https://www.state.gov/releases/office-of-the-spokesman/2026/02/secretary-of-state-marco-rubio-at-the-munich-security-conference | B82: the Russians are playing for time | C82: whether there is an outcome that Ukraine can live with and that Russia will accept | D82: There are some fundamental challenges between our countries and between the West and China | E82: To appease a climate cult, we have imposed energy policies on ourselves that are impoverishing our people | F82: an unprecedented wave of mass migration that threatens the cohesion of our societies | G82: a dangerous delusion…that we would now live in a world without borders | I82: For the United States and Europe, we belong together. | J82: today, on the most pressing matters before us, it has no answers and has played virtually no role | K82: we embraced a dogmatic vision of free and unfettered trade
A83: https://www.state.gov/releases/office-of-the-spokesman/2026/02/secretary-of-state-marco-rubio-remarks-to-press-5 | B83: we’ve imposed sanctions on Russia | C83: the reason why Ukraine’s been able to sustain this war is because the United States has provided and sold weapons to Ukraine | D83: It would be reckless and irresponsible for the United States and China not to have meetings | F83: has experienced mass migration from Cuba in the past | J83: The United Nations isn’t going to do it.
A84: https://www.state.gov/releases/office-of-the-spokesman/2026/05/joint-statement-by-members-of-the-shield-of-the-americas | L84: We cannot allow the overthrow of democratically elected leaders in our hemisphere
A85: https://www.state.gov/releases/office-of-the-spokesman/2026/09/protecting-the-sanctity-of-u-s-citizenshipa-new-visa-restriction-policy-for-those-who-engage-in-or-facilitate-birth-tourism | F85: The United States will not allow foreigners to exploit our immigration system
A86: https://www.state.gov/releases/office-of-the-spokesman/2025/09/secretary-of-state-marco-rubio-at-the-lech-walesa-solidarity-prize-awards-ceremony | L86: even when you make progress in democracy and in freedom, they have to be sustained and they have to endure
A87: https://www.state.gov/releases/office-of-the-spokesman/2026/07/additions-to-the-uyghur-forced-labor-prevention-act-entity-list | D87: goods tainted by forced labor of Uyghurs and other ethnic minorities in China | K87: leveling the playing field for American companies
A88: https://www.state.gov/releases/office-of-the-spokesman/2026/09/joint-statement-from-the-trilateral-meeting-of-the-united-states-of-america-japan-and-the-republic-of-korea-in-new-york-city-2 | J88: in accordance with the relevant United Nations Security Council resolutions
A89: https://www.state.gov/releases/office-of-the-spokesman/2026/08/release-of-robert-gilman | B89: We thank Russia for working with Special Envoy Steve Witkoff to release Mr. Gilman
A90: https://www.state.gov/releases/office-of-the-spokesman/2026/02/united-states-and-india-sign-pax-silica-declaration | K90: lowering barriers for startups and builders | L90: the world’s oldest and largest democracies remain the primary architects of the AI revolution
A91: https://www.state.gov/releases/office-of-the-spokesman/2026/05/advancing-u-s-rok-security-and-economic-cooperation | K91: the prompt resolution of market access barriers
A92: https://www.state.gov/releases/office-of-the-spokesman/2026/05/u-s-sanctions-tighten-grip-on-iran-china-oil-trade | D92: a China-based petroleum terminal operator that has imported tens of millions of barrels of sanctioned Iranian crude oil
A93: https://www.state.gov/releases/office-of-the-spokesman/2026/09/chile-national-day-2 | F93: combat the scourge of transnational crime and unchecked illegal immigration
A94: https://www.state.gov/releases/office-of-the-spokesman/2026/07/further-sanctions-on-the-cuban-regimes-sources-of-funding-and-tools-of-oppression | L94: promote democracy in Cuba
A95: https://www.state.gov/releases/office-of-the-spokesman/2026/07/joint-statement-on-the-tenth-anniversary-of-the-philippines-china-south-china-sea-arbitral-tribunal-award | D95: there is no legal basis for China’s expansive maritime claims in the South China Sea
A96: https://www.state.gov/releases/office-of-the-spokesman/2026/09/costa-rica-national-day-2 | F96: disrupt illegal immigration
A97: https://www.state.gov/releases/office-of-the-spokesman/2026/09/further-sanctions-on-cubas-mineral-wealth-and-military-modernization-apparatus | L97: promote democracy in Cuba
A98: https://www.state.gov/releases/office-of-the-spokesman/2025/10/two-year-anniversary-of-october-7th-attack | O98: The United States reaffirms its unwavering support for Israel’s right to exist, to defend itself, and to ensure the safety of its people.
A99: https://www.state.gov/releases/office-of-the-spokesman/2026/03/joint-statement-on-the-u-s-mongolia-annual-bilateral-consultation | L99: a shared interest in global peace, freedom, democracy, and economic prosperity
A100: https://www.state.gov/releases/office-of-the-spokesman/2026/08/joint-statement-by-secretary-of-health-and-human-services-robert-f-kennedy-and-secretary-of-state-marco-rubio-united-states-to-serve-as-secretariat-of-the-geneva-consensus-declaration | J100: to work together across the UN system to realize these values | N100: to protect life at all stages
...
